ai_asset_screener-0.1.1.dist-info/licenses/LICENSE
app/__init__.py
app/cache.py
app/console.py
app/edgar_extractor.py
app/ev_ebitda.py
app/ev_fair_value.py
app/float_value.py
app/forward_p_e.py
app/llm_util.py
app/p_fcf.py
app/sotp.py
app/yahoo.py
ai_asset_screener-0.1.1.dist-info/METADATA
ai_asset_screener-0.1.1.dist-info/WHEEL
ai_asset_screener-0.1.1.dist-info/entry_points.txt
ai_asset_screener-0.1.1.dist-info/top_level.txt
ai_asset_screener-0.1.1.dist-info/RECORD
