Metadata-Version: 2.4
Name: ai-asset-screener
Version: 0.1.1
Summary: CLI screener for US stocks based on LLM + financial metrics (P/FCF, EV/EBITDA, SOTP, float/EV)
Author-email: Evgeny Igumnov <igumnovnsk@gmail.com>
License: MIT
Keywords: finance,stocks,LLM,valuation,edgar,10-K,screener
Classifier: Programming Language :: Python :: 3
Classifier: License :: OSI Approved :: MIT License
Classifier: Operating System :: OS Independent
Classifier: Topic :: Office/Business :: Financial :: Investment
Classifier: Environment :: Console
Requires-Python: >=3.10
License-File: LICENSE
Requires-Dist: requests==2.32.3
Requires-Dist: yfinance==0.2.65
Requires-Dist: pandas==2.2.3
Requires-Dist: edgartools==4.8.1
Requires-Dist: langgraph==0.6.6
Requires-Dist: langchain_openai==0.3.31
Requires-Dist: langchain_mcp_adapters==0.1.9
Requires-Dist: mcp_server_calculator==0.2.0
Requires-Dist: argparse
Requires-Dist: python-dotenv==1.1.0
Dynamic: license-file
